README.md
setup.py
geoplotlibfixed/__init__.py
geoplotlibfixed/colors.py
geoplotlibfixed/core.py
geoplotlibfixed/layers.py
geoplotlibfixed/utils.py
geoplotlibfixed.egg-info/PKG-INFO
geoplotlibfixed.egg-info/SOURCES.txt
geoplotlibfixed.egg-info/dependency_links.txt
geoplotlibfixed.egg-info/requires.txt
geoplotlibfixed.egg-info/top_level.txt