Metadata-Version: 1.1
Name: geoplotlibfixed
Version: 0.0.1
Summary: python toolbox for geographic visualizations
Home-page: https://github.com/johnlanda/geoplotlib
Author: John Landa
Author-email: jonathanlanda@gmail.com
License: UNKNOWN
Download-URL: https://github.com/johnlanda/geoplotlib-fixed/archive/v0.0.1.tar.gz
Platform: UNKNOWN
